README.txt
bootstrap.py
buildout.cfg
setup.py
docs/HISTORY.txt
five/__init__.py
five.megrok.menu.egg-info/PKG-INFO
five.megrok.menu.egg-info/SOURCES.txt
five.megrok.menu.egg-info/dependency_links.txt
five.megrok.menu.egg-info/entry_points.txt
five.megrok.menu.egg-info/namespace_packages.txt
five.megrok.menu.egg-info/not-zip-safe
five.megrok.menu.egg-info/requires.txt
five.megrok.menu.egg-info/top_level.txt
five/megrok/__init__.py
five/megrok/menu/__init__.py
five/megrok/menu/component.py
five/megrok/menu/grokker.py
five/megrok/menu/meta.zcml
five/megrok/menu/testing.zcml
five/megrok/menu/tests/__init__.py
five/megrok/menu/tests/test_all.py
five/megrok/menu/tests/menus/__init__.py
five/megrok/menu/tests/menus/menus.py