Metadata-Version: 1.0
Name: five.megrok.menu
Version: 0.2
Summary: Grok support for browser menu in zope 2
Home-page: http://svn.zope.org/five.megrok.menu/trunk
Author: Jean-François Roche
Author-email: jfroche@affinitic.be
License: GPL
Platform: UNKNOWN
Classifier: Environment :: Web Environment
Classifier: Intended Audience :: Developers
Classifier: Programming Language :: Python
Classifier: License :: OSI Approved :: Zope Public License
Classifier: Topic :: Software Development :: Libraries :: Python Modules
Classifier: Framework :: Zope2
